__init__.py
erewhon_astro/__init__.py
erewhon_astro/plate_solve.py
erewhon_astro-0.7.0.dist-info/licenses/LICENSE
erewhon_astro-0.7.0.dist-info/METADATA
erewhon_astro-0.7.0.dist-info/WHEEL
erewhon_astro-0.7.0.dist-info/top_level.txt
erewhon_astro-0.7.0.dist-info/RECORD
